[
    {
        "latitude": 44.514365857,
        "longitude": -80.355189778
    },
    {
        "latitude": 44.514333,
        "longitude": -80.355184413
    },
    {
        "latitude": 44.514300143,
        "longitude": -80.35518894
    },
    {
        "latitude": 44.514267202,
        "longitude": -80.355198327
    },
    {
        "latitude": 44.514234345,
        "longitude": -80.35520277
    },
    {
        "latitude": 44.514198219,
        "longitude": -80.355202267
    },
    {
        "latitude": 44.514165279,
        "longitude": -80.355211655
    },
    {
        "latitude": 44.514129153,
        "longitude": -80.355211152
    },
    {
        "latitude": 44.514096295,
        "longitude": -80.355215594
    },
    {
        "latitude": 44.514063355,
        "longitude": -80.35522012
    },
    {
        "latitude": 44.514021529,
        "longitude": -80.355212661
    },
    {
        "latitude": 44.513997724,
        "longitude": -80.355214253
    },
    {
        "latitude": 44.513964867,
        "longitude": -80.355208972
    },
    {
        "latitude": 44.513928741,
        "longitude": -80.35520847
    },
    {
        "latitude": 44.513895884,
        "longitude": -80.355207967
    },
    {
        "latitude": 44.513859507,
        "longitude": -80.355207212
    },
    {
        "latitude": 44.513822207,
        "longitude": -80.355209978
    },
    {
        "latitude": 44.51378935,
        "longitude": -80.355212828
    },
    {
        "latitude": 44.513758672,
        "longitude": -80.355212409
    },
    {
        "latitude": 44.513723636,
        "longitude": -80.355215175
    },
    {
        "latitude": 44.513690779,
        "longitude": -80.355214756
    },
    {
        "latitude": 44.513664544,
        "longitude": -80.355207883
    },
    {
        "latitude": 44.513629843,
        "longitude": -80.355194556
    },
    {
        "latitude": 44.513596985,
        "longitude": -80.35518433
    },
    {
        "latitude": 44.513564212,
        "longitude": -80.355174104
    },
    {
        "latitude": 44.513531439,
        "longitude": -80.355158849
    },
    {
        "latitude": 44.513502019,
        "longitude": -80.355133954
    },
    {
        "latitude": 44.513469245,
        "longitude": -80.355118783
    },
    {
        "latitude": 44.513436556,
        "longitude": -80.355098667
    },
    {
        "latitude": 44.513403783,
        "longitude": -80.355078634
    },
    {
        "latitude": 44.513371009,
        "longitude": -80.355063379
    },
    {
        "latitude": 44.51333832,
        "longitude": -80.355043346
    },
    {
        "latitude": 44.513305547,
        "longitude": -80.355023229
    },
    {
        "latitude": 44.513272773,
        "longitude": -80.355013004
    },
    {
        "latitude": 44.51324,
        "longitude": -80.355002694
    },
    {
        "latitude": 44.513207143,
        "longitude": -80.354997329
    },
    {
        "latitude": 44.51317437,
        "longitude": -80.354987103
    },
    {
        "latitude": 44.513141597,
        "longitude": -80.354971932
    },
    {
        "latitude": 44.513108823,
        "longitude": -80.354956761
    },
    {
        "latitude": 44.51307605,
        "longitude": -80.354946451
    },
    {
        "latitude": 44.513043193,
        "longitude": -80.354936225
    },
    {
        "latitude": 44.51301042,
        "longitude": -80.354921054
    },
    {
        "latitude": 44.512977647,
        "longitude": -80.354910828
    },
    {
        "latitude": 44.51294479,
        "longitude": -80.354905464
    },
    {
        "latitude": 44.512912016,
        "longitude": -80.354900099
    },
    {
        "latitude": 44.512879159,
        "longitude": -80.35489968
    },
    {
        "latitude": 44.512846302,
        "longitude": -80.354899177
    },
    {
        "latitude": 44.512813361,
        "longitude": -80.35491351
    },
    {
        "latitude": 44.51278042,
        "longitude": -80.354917953
    },
    {
        "latitude": 44.512747563,
        "longitude": -80.354927341
    },
    {
        "latitude": 44.512714706,
        "longitude": -80.354926921
    },
    {
        "latitude": 44.512681765,
        "longitude": -80.354931364
    },
    {
        "latitude": 44.512648908,
        "longitude": -80.354935806
    },
    {
        "latitude": 44.512615968,
        "longitude": -80.354950139
    },
    {
        "latitude": 44.512583027,
        "longitude": -80.354964389
    },
    {
        "latitude": 44.512550086,
        "longitude": -80.354978638
    },
    {
        "latitude": 44.512517145,
        "longitude": -80.354992971
    },
    {
        "latitude": 44.512484204,
        "longitude": -80.35500722
    },
    {
        "latitude": 44.512451263,
        "longitude": -80.355026415
    },
    {
        "latitude": 44.512418322,
        "longitude": -80.355035802
    },
    {
        "latitude": 44.512385381,
        "longitude": -80.355050135
    },
    {
        "latitude": 44.512352357,
        "longitude": -80.35506933
    },
    {
        "latitude": 44.512319416,
        "longitude": -80.355083579
    },
    {
        "latitude": 44.512286559,
        "longitude": -80.355088022
    },
    {
        "latitude": 44.512240626,
        "longitude": -80.355087519
    },
    {
        "latitude": 44.512207685,
        "longitude": -80.355101852
    },
    {
        "latitude": 44.512174744,
        "longitude": -80.355111239
    },
    {
        "latitude": 44.512141803,
        "longitude": -80.355120543
    },
    {
        "latitude": 44.512108946,
        "longitude": -80.355129931
    },
    {
        "latitude": 44.512076005,
        "longitude": -80.355144264
    },
    {
        "latitude": 44.512043064,
        "longitude": -80.355158513
    },
    {
        "latitude": 44.512010124,
        "longitude": -80.355172846
    },
    {
        "latitude": 44.511973914,
        "longitude": -80.35518215
    },
    {
        "latitude": 44.511936698,
        "longitude": -80.355184916
    },
    {
        "latitude": 44.511914738,
        "longitude": -80.355194388
    },
    {
        "latitude": 44.51187836,
        "longitude": -80.355215259
    },
    {
        "latitude": 44.511845503,
        "longitude": -80.355219701
    },
    {
        "latitude": 44.511812562,
        "longitude": -80.355229089
    },
    {
        "latitude": 44.511779621,
        "longitude": -80.355243338
    },
    {
        "latitude": 44.51174668,
        "longitude": -80.355257671
    },
    {
        "latitude": 44.511713823,
        "longitude": -80.355267059
    },
    {
        "latitude": 44.511680882,
        "longitude": -80.355281308
    },
    {
        "latitude": 44.511647858,
        "longitude": -80.355300503
    },
    {
        "latitude": 44.511614833,
        "longitude": -80.355324643
    },
    {
        "latitude": 44.511581892,
        "longitude": -80.355338892
    },
    {
        "latitude": 44.511548951,
        "longitude": -80.355353225
    },
    {
        "latitude": 44.511516094,
        "longitude": -80.355362613
    },
    {
        "latitude": 44.511483153,
        "longitude": -80.355376862
    },
    {
        "latitude": 44.511453481,
        "longitude": -80.35538625
    },
    {
        "latitude": 44.511420541,
        "longitude": -80.355405444
    }
]